openai_embeddings_model/VERSION
openai_embeddings_model/__init__.py
openai_embeddings_model/embedding_model.py
openai_embeddings_model-0.4.0.dist-info/LICENSE
openai_embeddings_model-0.4.0.dist-info/METADATA
openai_embeddings_model-0.4.0.dist-info/WHEEL
openai_embeddings_model-0.4.0.dist-info/RECORD
